py_dataset/__init__.py
py_dataset/dataset.py
py_dataset/libdataset.py
py_dataset/lib/libdataset-arm.dylib
py_dataset/lib/libdataset.dll
py_dataset/lib/libdataset.dylib
py_dataset/lib/libdataset.h
py_dataset/lib/libdataset.so
py_dataset-1.0.1.dist-info/LICENSE
py_dataset-1.0.1.dist-info/METADATA
py_dataset-1.0.1.dist-info/WHEEL
py_dataset-1.0.1.dist-info/top_level.txt
py_dataset-1.0.1.dist-info/RECORD
