Metadata-Version: 2.1
Name: py-dataset
Version: 1.0.1
Summary: A command line tool for working with JSON documents on local disc
Home-page: https://github.com/caltechlibrary/py_dataset
Author: Robert Doiel, Thomas E Morrell
Author-email: rsdoiel@caltech.edu, tmorrell@caltech.edu
License: https://data.caltech.edu/license
Download-URL: https://github.com/caltechlibrary/py_dataset/releases
Keywords: GitHub,metadata,data,software,json
Platform: UNKNOWN
Classifier: Development Status :: 4 - Beta
Classifier: Environment :: Console
Classifier: Programming Language :: Python
Classifier: Programming Language :: Python :: 3
Classifier: Programming Language :: Other
Classifier: Intended Audience :: Science/Research
Classifier: Topic :: Scientific/Engineering
Classifier: License :: OSI Approved :: BSD License
Classifier: Operating System :: Microsoft :: Windows :: Windows 10
Classifier: Operating System :: POSIX :: Linux
Classifier: Operating System :: MacOS :: MacOS X
Requires-Python: >=3.6.0
License-File: LICENSE
